IMProToo/__init__.py
IMProToo/core.py
IMProToo/tools.py
IMProToo-0.107.dist-info/LICENSE
IMProToo-0.107.dist-info/METADATA
IMProToo-0.107.dist-info/WHEEL
IMProToo-0.107.dist-info/top_level.txt
IMProToo-0.107.dist-info/RECORD
