Metadata-Version: 2.1
Name: IMProToo
Version: 0.107
Author: Maximilian Maahn
License: GNU General Public License 3
Classifier: Development Status :: 4 - Beta
Classifier: Topic :: Utilities
Classifier: License :: OSI Approved :: GNU General Public License v3 (GPLv3)
Classifier: Operating System :: OS Independent
Classifier: Programming Language :: Python
Classifier: Intended Audience :: Science/Research
Classifier: Topic :: Scientific/Engineering
License-File: LICENSE
Requires-Dist: numpy
Requires-Dist: matplotlib
Requires-Dist: netCDF4
Requires-Dist: scipy
